LICENSE
MANIFEST.in
README.md
setup.py
redis_clu.egg-info/PKG-INFO
redis_clu.egg-info/SOURCES.txt
redis_clu.egg-info/dependency_links.txt
redis_clu.egg-info/entry_points.txt
redis_clu.egg-info/pbr.json
redis_clu.egg-info/requires.txt
redis_clu.egg-info/top_level.txt
redisclu/__init__.py
redisclu/cluster.py
redisclu/exceptions.py
redisclu/failover.py
redisclu/node.py
redisclu/utils.py
redisclu/cli/__init__.py
redisclu/cli/commands.py
redisclu/cli/helper.py