Metadata-Version: 1.1
Name: redis-clu
Version: 0.0.7
Summary: Redis Cluster Management Tool
Home-page: https://github.com/baranbartu/redis-clu
Author: Baran Bartu Demirci
Author-email: bbartu.demirci@gmail.com
License: MIT
Download-URL: https://github.com/baranbartu/redis-clu/tarball/0.0.7
Keywords: redis cluster management replication master slave
Platform: UNKNOWN
